distrax/__init__.py
distrax/distrax_test.py
distrax/_src/__init__.py
distrax/_src/bijectors/__init__.py
distrax/_src/bijectors/bijector.py
distrax/_src/bijectors/bijector_from_tfp.py
distrax/_src/bijectors/bijector_from_tfp_test.py
distrax/_src/bijectors/bijector_test.py
distrax/_src/bijectors/block.py
distrax/_src/bijectors/block_test.py
distrax/_src/bijectors/chain.py
distrax/_src/bijectors/chain_test.py
distrax/_src/bijectors/diag_linear.py
distrax/_src/bijectors/diag_linear_test.py
distrax/_src/bijectors/diag_plus_low_rank_linear.py
distrax/_src/bijectors/diag_plus_low_rank_linear_test.py
distrax/_src/bijectors/gumbel_cdf.py
distrax/_src/bijectors/gumbel_cdf_test.py
distrax/_src/bijectors/inverse.py
distrax/_src/bijectors/inverse_test.py
distrax/_src/bijectors/lambda_bijector.py
distrax/_src/bijectors/lambda_bijector_test.py
distrax/_src/bijectors/linear.py
distrax/_src/bijectors/linear_test.py
distrax/_src/bijectors/lower_upper_triangular_affine.py
distrax/_src/bijectors/lower_upper_triangular_affine_test.py
distrax/_src/bijectors/masked_coupling.py
distrax/_src/bijectors/masked_coupling_test.py
distrax/_src/bijectors/rational_quadratic_spline.py
distrax/_src/bijectors/rational_quadratic_spline_float64_test.py
distrax/_src/bijectors/rational_quadratic_spline_test.py
distrax/_src/bijectors/scalar_affine.py
distrax/_src/bijectors/scalar_affine_test.py
distrax/_src/bijectors/shift.py
distrax/_src/bijectors/shift_test.py
distrax/_src/bijectors/sigmoid.py
distrax/_src/bijectors/sigmoid_test.py
distrax/_src/bijectors/split_coupling.py
distrax/_src/bijectors/split_coupling_test.py
distrax/_src/bijectors/tanh.py
distrax/_src/bijectors/tanh_test.py
distrax/_src/bijectors/tfp_compatible_bijector.py
distrax/_src/bijectors/tfp_compatible_bijector_test.py
distrax/_src/bijectors/triangular_linear.py
distrax/_src/bijectors/triangular_linear_test.py
distrax/_src/bijectors/unconstrained_affine.py
distrax/_src/bijectors/unconstrained_affine_test.py
distrax-0.1.7.dist-info/licenses/LICENSE
distrax-0.1.7.dist-info/WHEEL
distrax-0.1.7.dist-info/METADATA
distrax-0.1.7.dist-info/RECORD
